django_inertia/__init__.py
django_inertia/apps.py
django_inertia/assertions.py
django_inertia/core.py
django_inertia/middleware.py
django_inertia/props.py
django_inertia/settings.py
django_inertia/templatetags/__init__.py
django_inertia/templatetags/inertia_tags.py
django_inertia-1.3.0.dist-info/LICENSE
django_inertia-1.3.0.dist-info/METADATA
django_inertia-1.3.0.dist-info/WHEEL
django_inertia-1.3.0.dist-info/top_level.txt
django_inertia-1.3.0.dist-info/RECORD
