Metadata-Version: 2.1
Name: django-inertia
Version: 1.3.0
Summary: Server-side Django adapter for Inertia.js
Home-page: https://github.com/girardinsamuel/django-inertia
Author: Samuel Girardin
Author-email: samuelgirardin@pm.me
License: MIT license
Keywords: Django,Python,Inertia.js
Platform: UNKNOWN
Classifier: Intended Audience :: Developers
Classifier: License :: OSI Approved :: MIT License
Classifier: Programming Language :: Python :: 3.7
Classifier: Programming Language :: Python :: 3.8
Classifier: Programming Language :: Python :: 3.9
Classifier: Programming Language :: Python :: 3.10
Classifier: Topic :: Software Development :: Libraries :: Application Frameworks
Classifier: Topic :: Software Development :: Libraries :: Python Modules
Classifier: Framework :: Django
Requires-Python: >=3.7.0
License-File: LICENSE
Requires-Dist: django (<5,>=3)
Requires-Dist: dotty-dict (==1.3.0)
Provides-Extra: dev
Requires-Dist: black ; extra == 'dev'
Requires-Dist: flake8 ; extra == 'dev'
Requires-Dist: flake8-isort ; extra == 'dev'
Requires-Dist: twine ; extra == 'dev'
Requires-Dist: wheel ; extra == 'dev'
Requires-Dist: pytest ; extra == 'dev'
Requires-Dist: pytest-django ; extra == 'dev'
Requires-Dist: pytest-cov ; extra == 'dev'
Requires-Dist: coverage ; extra == 'dev'
Requires-Dist: bump2version ; extra == 'dev'
